MANIFEST.in
README.md
setup.cfg
setup.py
facsimile/VERSION
facsimile/requirements-test.txt
facsimile/requirements.txt
twentyc.rpc.egg-info/PKG-INFO
twentyc.rpc.egg-info/SOURCES.txt
twentyc.rpc.egg-info/dependency_links.txt
twentyc.rpc.egg-info/namespace_packages.txt
twentyc.rpc.egg-info/not-zip-safe
twentyc.rpc.egg-info/requires.txt
twentyc.rpc.egg-info/top_level.txt
twentyc/rpc/__init__.py
twentyc/rpc/client.py