Metadata-Version: 1.1
Name: twentyc.rpc
Version: 0.4.0
Summary: client for 20c's RESTful API
Home-page: https://github.com/20c/twentyc.rpc
Author: 20C
Author-email: code@20c.com
License: LICENSE
Download-URL: https://github.com/20c/twentyc.rpc/0.4.0
Platform: UNKNOWN
Classifier: Development Status :: 4 - Beta
Classifier: Intended Audience :: Developers
Classifier: Topic :: Internet
Classifier: License :: OSI Approved :: Apache Software License
Classifier: Topic :: Software Development :: Libraries :: Python Modules
